llama_index/packs/rag_fusion_query_pipeline/__init__.py
llama_index/packs/rag_fusion_query_pipeline/base.py
llama_index_packs_query-0.3.1.dist-info/METADATA
llama_index_packs_query-0.3.1.dist-info/WHEEL
llama_index_packs_query-0.3.1.dist-info/licenses/LICENSE
llama_index_packs_query-0.3.1.dist-info/RECORD
