Metadata-Version: 2.4
Name: llama-index-packs-query
Version: 0.3.1
Summary: llama-index packs query integration
Author-email: Your Name <you@example.com>
Maintainer: jerryjliu
License-Expression: MIT
License-File: LICENSE
Keywords: fusion,pipeline,query,rag
Requires-Python: <4.0,>=3.9
Requires-Dist: llama-index-core<0.13,>=0.12.0
Requires-Dist: llama-index-llms-openai<0.5,>=0.4.0
